my_csvtojson_converter/__init__.py
my_csvtojson_converter/converter.py
my_csvtojson_converter-0.1.2.dist-info/entry_points.txt
my_csvtojson_converter-0.1.2.dist-info/WHEEL
my_csvtojson_converter-0.1.2.dist-info/METADATA
my_csvtojson_converter-0.1.2.dist-info/RECORD
