Metadata-Version: 2.1
Name: my-csvtojson-converter
Version: 0.1.2
Summary: Converte arquivos .csv para .json. Publicado apenas para fins educativos da PUC/Minas, classe de Pós Graduação.
Author: Mirian Machado
Author-email: miriancosta.m@outlook.com
Requires-Python: >=3.10,<4.0
Classifier: Programming Language :: Python :: 3
Classifier: Programming Language :: Python :: 3.10
Requires-Dist: click (>=8.0.3,<9.0.0)
